jujuba/__init__.py
jujuba/module1_name/__init__.py
jujuba/module1_name/file1_name.py
jujuba/module1_name/file2_name.py
jujuba/module2_name/__init__.py
jujuba/module2_name/file1_name.py
jujuba/module2_name/file2_name.py
jujuba-0.0.1.dist-info/METADATA
jujuba-0.0.1.dist-info/WHEEL
jujuba-0.0.1.dist-info/top_level.txt
jujuba-0.0.1.dist-info/RECORD
