Metadata-Version: 2.1
Name: jujuba
Version: 0.0.1
Summary: My short description
Home-page: https://github.com/alecsandergr/dio
Author: my_name
Author-email: leelecko@gmail.com
License: UNKNOWN
Platform: UNKNOWN
Requires-Python: >=3.8
